voicemode_install/__init__.py
voicemode_install/checker.py
voicemode_install/cli.py
voicemode_install/dependencies.yaml
voicemode_install/hardware.py
voicemode_install/installer.py
voicemode_install/logger.py
voicemode_install/system.py
voice_mode_install-7.4.0.dist-info/METADATA
voice_mode_install-7.4.0.dist-info/WHEEL
voice_mode_install-7.4.0.dist-info/entry_points.txt
voice_mode_install-7.4.0.dist-info/RECORD
