Metadata-Version: 2.4
Name: voice-mode-install
Version: 7.4.0
Summary: Installer for VoiceMode - handles system dependencies and installation
Project-URL: Homepage, https://github.com/mbailey/voicemode
Project-URL: Repository, https://github.com/mbailey/voicemode
Project-URL: Issues, https://github.com/mbailey/voicemode/issues
Author-email: mbailey <mbailey@example.com>
License: MIT
Keywords: installer,mcp,setup,voice,voicemode
Classifier: Development Status :: 4 - Beta
Classifier: Intended Audience :: Developers
Classifier: License :: OSI Approved :: MIT License
Classifier: Programming Language :: Python :: 3
Classifier: Programming Language :: Python :: 3.10
Classifier: Programming Language :: Python :: 3.11
Classifier: Programming Language :: Python :: 3.12
Classifier: Programming Language :: Python :: 3.13
Classifier: Topic :: Software Development :: Libraries
Classifier: Topic :: System :: Installation/Setup
Requires-Python: >=3.10
Requires-Dist: click>=8.0.0
Requires-Dist: psutil>=5.9.0
Requires-Dist: pyyaml>=6.0.0
